kbtcal/__init__.py
kbtcal/datasets.py
kbtcal-1.5.dist-info/LICENSE.txt
kbtcal-1.5.dist-info/METADATA
kbtcal-1.5.dist-info/WHEEL
kbtcal-1.5.dist-info/top_level.txt
kbtcal-1.5.dist-info/RECORD
